[
  {
    "startTime": 20.7,
    "words": [
      {
        "text": "あー",
        "furigana": null
      },
      {
        "text": "、",
        "furigana": null
      },
      {
        "text": "恋",
        "furigana": "こい"
      },
      {
        "text": "の",
        "furigana": null
      },
      {
        "text": "定義",
        "furigana": "ていぎ"
      },
      {
        "text": "がわかんない",
        "furigana": null
      }
    ],
    "translation": "啊,搞不懂什麼是戀愛"
  },
  {
    "startTime": 22.86,
    "words": [
      {
        "text": "まず",
        "furigana": null
      },
      {
        "text": "スキ",
        "furigana": "すき"
      },
      {
        "text": "って",
        "furigana": null
      },
      {
        "text": "基準",
        "furigana": "きじゅん"
      },
      {
        "text": "もわかんない",
        "furigana": null
      }
    ],
    "translation": "首先連什麼是喜歡都不知道"
  },
  {
    "startTime": 24.36,
    "words": [
      {
        "text": "要",
        "furigana": "よう"
      },
      {
        "text": "は、",
        "furigana": null
      },
      {
        "text": "恋",
        "furigana": "こい"
      },
      {
        "text": "してるときが",
        "furigana": null
      },
      {
        "text": "恋",
        "furigana": "こい"
      },
      {
        "text": "らしい",
        "furigana": null
      }
    ],
    "translation": "總之,戀愛的當下就是在戀愛"
  },
  {
    "startTime": 26.46,
    "words": [
      {
        "text": "愛",
        "furigana": "あい"
      },
      {
        "text": "は",
        "furigana": null
      },
      {
        "text": "計算",
        "furigana": "けいさん"
      },
      {
        "text": "じゃ",
        "furigana": null
      },
      {
        "text": "解",
        "furigana": "と"
      },
      {
        "text": "け",
        "furigana": null
      },
      {
        "text": "ない",
        "furigana": null
      }
    ],
    "translation": "愛情無法靠計算來解開"
  },
  {
    "startTime": 29.42,
    "words": [
      {
        "text": "まず",
        "furigana": null
      },
      {
        "text": "普通",
        "furigana": "ふつう"
      },
      {
        "text": "の",
        "furigana": null
      },
      {
        "text": "計算",
        "furigana": "けいさん"
      },
      {
        "text": "も",
        "furigana": null
      },
      {
        "text": "解",
        "furigana": "と"
      },
      {
        "text": "けない",
        "furigana": null
      }
    ],
    "translation": "我連一般的計算都求解不開"
  },
  {
    "startTime": 31.12,
    "words": [
      {
        "text": "要",
        "furigana": "よう"
      },
      {
        "text": "は、そんな ",
        "furigana": null
      },
      {
        "text": "状態",
        "furigana": "じょうたい"
      },
      {
        "text": " が",
        "furigana": null
      },
      {
        "text": "愛",
        "furigana": "あい"
      },
      {
        "text": "らしい",
        "furigana": null
      }
    ],
    "translation": "總之,這樣的狀況貌似是愛情"
  },
  {
    "startTime": 32.86,
    "words": [
      {
        "text": "アイノウ",
        "furigana": "あいのう"
      },
      {
        "text": "? ",
        "furigana": null
      },
      {
        "text": "ユーノウ",
        "furigana": "ゆーのう"
      },
      {
        "text": "?",
        "furigana": null
      }
    ],
    "translation": "我懂得? 你懂嗎?"
  },
  {
    "startTime": 33.78,
    "words": [
      {
        "text": "もう",
        "furigana": null
      },
      {
        "text": "大抵",
        "furigana": "たいてい"
      },
      {
        "text": "の",
        "furigana": null
      },
      {
        "text": "事象",
        "furigana": "じしょう"
      },
      {
        "text": "において Q があって A を",
        "furigana": null
      },
      {
        "text": "出",
        "furigana": "だ"
      },
      {
        "text": "して",
        "furigana": null
      },
      {
        "text": "解",
        "furigana": "と"
      },
      {
        "text": "けるのに",
        "furigana": null
      }
    ],
    "translation": "明明可以通過類似事件藉由Q解出A"
  },
  {
    "startTime": 38.2,
    "words": [
      {
        "text": "ふめいりょう",
        "furigana": null
      }
    ],
    "translation": "不明瞭 )"
  },
  {
    "startTime": 43.36,
    "words": [
      {
        "text": "DAZING!! ",
        "furigana": null
      },
      {
        "text": "モーション",
        "furigana": "もーしょん"
      },
      {
        "text": "は ",
        "furigana": null
      },
      {
        "text": "相対性",
        "furigana": "そうたいせい"
      },
      {
        "text": " に",
        "furigana": null
      },
      {
        "text": "ステイ",
        "furigana": "すてい"
      }
    ],
    "translation": "DAZING!! 舉止保留相對性"
  },
  {
    "startTime": 48.24,
    "words": [
      {
        "text": "チューリングラブ",
        "furigana": "ちゅーりんぐらぶ"
      },
      {
        "text": " ",
        "furigana": null
      },
      {
        "text": "見",
        "furigana": "み"
      },
      {
        "text": "つ",
        "furigana": null
      },
      {
        "text": "めあったったって",
        "furigana": null
      },
      {
        "text": "解",
        "furigana": "と"
      },
      {
        "text": "け",
        "furigana": null
      },
      {
        "text": "ない",
        "furigana": null
      },
      {
        "text": "メロウ",
        "furigana": "めろう"
      }
    ],
    "translation": "Turing Love 互相凝視也解不開的甜愛滋味"
  },
  {
    "startTime": 51.78,
    "words": [
      {
        "text": "ワットイズラブ",
        "furigana": "わっといずらぶ"
      },
      {
        "text": " ",
        "furigana": null
      },
      {
        "text": "いま",
        "furigana": null
      },
      {
        "text": " 123 ",
        "furigana": null
      },
      {
        "text": "で",
        "furigana": null
      },
      {
        "text": "証",
        "furigana": "しょう"
      },
      {
        "text": "そ",
        "furigana": null
      },
      {
        "text": "うか",
        "furigana": null
      }
    ],
    "translation": "What is Love 此刻用123來證明吧"
  },
  {
    "startTime": 55.08,
    "words": [
      {
        "text": "言葉",
        "furigana": "ことば"
      },
      {
        "text": "で",
        "furigana": null
      },
      {
        "text": "生",
        "furigana": "う"
      },
      {
        "text": "み",
        "furigana": null
      },
      {
        "text": "出",
        "furigana": "だ"
      },
      {
        "text": "す",
        "furigana": null
      },
      {
        "text": "クエスチョン",
        "furigana": "くえすちょん"
      },
      {
        "text": " (",
        "furigana": null
      },
      {
        "text": "クエスチョン",
        "furigana": "くえすちょん"
      },
      {
        "text": "!)",
        "furigana": null
      }
    ],
    "translation": "言語之中所產生的問題 (Question!)"
  },
  {
    "startTime": 56.74,
    "words": [
      {
        "text": "ハート",
        "furigana": "はーと"
      },
      {
        "text": "で",
        "furigana": null
      },
      {
        "text": "高鳴",
        "furigana": "たかな"
      },
      {
        "text": "る",
        "furigana": null
      },
      {
        "text": "アンサー",
        "furigana": "あんさー"
      },
      {
        "text": " (",
        "furigana": null
      },
      {
        "text": "アンサー",
        "furigana": "あんさー"
      },
      {
        "text": "!)",
        "furigana": null
      }
    ],
    "translation": "心情激動所提出的解答 (Answer!)"
  },
  {
    "startTime": 58.94,
    "words": [
      {
        "text": "測",
        "furigana": "はか"
      },
      {
        "text": "ったって",
        "furigana": null
      },
      {
        "text": "不確定性",
        "furigana": "ふかくていせい"
      },
      {
        "text": " ぼくらの BPM",
        "furigana": null
      }
    ],
    "translation": "無法經由測量得出 我們的 BPM"
  },
  {
    "startTime": 61.76,
    "words": [
      {
        "text": "チューリングラブ",
        "furigana": "ちゅーりんぐらぶ"
      },
      {
        "text": " ",
        "furigana": null
      },
      {
        "text": "宙",
        "furigana": "ちゅう"
      },
      {
        "text": " ",
        "furigana": null
      },
      {
        "text": "に",
        "furigana": null
      },
      {
        "text": "舞",
        "furigana": "ま"
      },
      {
        "text": "っ",
        "furigana": null
      },
      {
        "text": "たったって",
        "furigana": null
      },
      {
        "text": "信",
        "furigana": "しん"
      },
      {
        "text": "じ",
        "furigana": null
      },
      {
        "text": "ないけど",
        "furigana": null
      }
    ],
    "translation": "Turing Love 即使在空中漫天飛舞也無法確信"
  },
  {
    "startTime": 65.14,
    "words": [
      {
        "text": "フォーリンラブ",
        "furigana": "ふぉーりんらぶ"
      },
      {
        "text": " いまは ABC すら",
        "furigana": null
      },
      {
        "text": "バグ",
        "furigana": "ばぐ"
      },
      {
        "text": "りそうだ",
        "furigana": null
      }
    ],
    "translation": "Fall in Love 現在連ABC都出現了故障"
  },
  {
    "startTime": 68.56,
    "words": [
      {
        "text": "なんでか",
        "furigana": null
      },
      {
        "text": "教",
        "furigana": "おし"
      },
      {
        "text": "えて",
        "furigana": null
      },
      {
        "text": "オイラー",
        "furigana": "おいらー"
      },
      {
        "text": " (",
        "furigana": null
      },
      {
        "text": "オイラー",
        "furigana": "おいらー"
      },
      {
        "text": "!)",
        "furigana": null
      }
    ],
    "translation": "請告訴我答案吧 歐拉 (Euler!)"
  },
  {
    "startTime": 70.32,
    "words": [
      {
        "text": "感想",
        "furigana": "かんそう"
      },
      {
        "text": "きかせて",
        "furigana": null
      },
      {
        "text": "フェルマー",
        "furigana": "ふぇるまー"
      },
      {
        "text": " (",
        "furigana": null
      },
      {
        "text": "フェルマー",
        "furigana": "ふぇるまー"
      },
      {
        "text": "!)",
        "furigana": null
      }
    ],
    "translation": "發表一下感想吧 費馬 (Fermat!)"
  },
  {
    "startTime": 74.24,
    "words": [
      {
        "text": "予測",
        "furigana": "よそく"
      },
      {
        "text": "不可能性",
        "furigana": "ふかのうせい"
      },
      {
        "text": " ",
        "furigana": null
      },
      {
        "text": "いま",
        "furigana": null
      },
      {
        "text": "触",
        "furigana": "ふ"
      },
      {
        "text": "れて",
        "furigana": null
      },
      {
        "text": "みる",
        "furigana": null
      }
    ],
    "translation": "我嘗試著觸碰 這不可預測性"
  },
  {
    "startTime": 74.9,
    "words": [
      {
        "text": "さあ ",
        "furigana": null
      },
      {
        "text": "証明",
        "furigana": "しょうめい"
      },
      {
        "text": " しよう ( ",
        "furigana": null
      },
      {
        "text": "証明",
        "furigana": "しょうめい"
      },
      {
        "text": " しよう) ",
        "furigana": null
      },
      {
        "text": "間違",
        "furigana": "まちが"
      },
      {
        "text": "いのないように",
        "furigana": null
      }
    ],
    "translation": "來證明吧 (證明吧) 為了不要弄錯"
  },
  {
    "startTime": 78.66,
    "words": [
      {
        "text": "証明",
        "furigana": "しょうめい"
      },
      {
        "text": " しよう ( ",
        "furigana": null
      },
      {
        "text": "証明",
        "furigana": "しょうめい"
      },
      {
        "text": " しよう) この ",
        "furigana": null
      },
      {
        "text": "感情",
        "furigana": "かんじょうぜんぶ"
      },
      {
        "text": " ",
        "furigana": null
      },
      {
        "text": "全部全部",
        "furigana": "ぜんぶ"
      }
    ],
    "translation": "證明吧 (證明吧) 將這份感情的全部全部"
  },
  {
    "startTime": 82.1,
    "words": [
      {
        "text": "証明",
        "furigana": "しょうめい"
      },
      {
        "text": " しよう ( ",
        "furigana": null
      },
      {
        "text": "証明",
        "furigana": "しょうめい"
      },
      {
        "text": " しよう) ",
        "furigana": null
      },
      {
        "text": "正解",
        "furigana": "せいかい"
      },
      {
        "text": "があるなら",
        "furigana": null
      }
    ],
    "translation": "證明吧 (證明吧) 如果有正確解答"
  },
  {
    "startTime": 85.44,
    "words": [
      {
        "text": "証明",
        "furigana": "しょうめい"
      },
      {
        "text": " しよう ( ",
        "furigana": null
      },
      {
        "text": "証明",
        "furigana": "しょうめい"
      },
      {
        "text": " しよう) ",
        "furigana": null
      },
      {
        "text": "シンプル",
        "furigana": "しんぷる"
      },
      {
        "text": "な Q.E.D.",
        "furigana": null
      }
    ],
    "translation": "證明吧 (證明吧) 簡單的 Q.E.D."
  },
  {
    "startTime": 95.94,
    "words": [
      {
        "text": "今日",
        "furigana": "きょう"
      },
      {
        "text": "こそ ",
        "furigana": null
      },
      {
        "text": "証明",
        "furigana": "しょうめい"
      },
      {
        "text": " したい! (しよう!)",
        "furigana": null
      }
    ],
    "translation": "就想在今日證明! (嘗試吧!)"
  },
  {
    "startTime": 97.3,
    "words": [
      {
        "text": "目",
        "furigana": "め"
      },
      {
        "text": "に",
        "furigana": null
      },
      {
        "text": "視",
        "furigana": "み"
      },
      {
        "text": "えない ",
        "furigana": null
      },
      {
        "text": "無理難題",
        "furigana": "むりなんだい"
      },
      {
        "text": "を",
        "furigana": null
      }
    ],
    "translation": "解開超脫現實的 不合理難題"
  },
  {
    "startTime": 99.06,
    "words": [
      {
        "text": "ASAP! ",
        "furigana": null
      },
      {
        "text": "導",
        "furigana": "みちび"
      },
      {
        "text": " き",
        "furigana": null
      },
      {
        "text": "出",
        "furigana": "だ"
      },
      {
        "text": "したい たどり",
        "furigana": null
      },
      {
        "text": "着",
        "furigana": "つ"
      },
      {
        "text": "きたい ",
        "furigana": null
      },
      {
        "text": "最適解",
        "furigana": "さいてきかい"
      },
      {
        "text": " へ",
        "furigana": null
      }
    ],
    "translation": "ASAP! 想要引導出來想要抵達到問題的最佳解答"
  },
  {
    "startTime": 103.08,
    "words": [
      {
        "text": "何度空回",
        "furigana": "なんどからまわ"
      },
      {
        "text": "ったって ぶつかっちゃったって",
        "furigana": null
      }
    ],
    "translation": "即使遇到瓶頸再多次"
  },
  {
    "startTime": 105.6,
    "words": [
      {
        "text": "不可思議",
        "furigana": "ふかしぎ"
      },
      {
        "text": "なこの",
        "furigana": null
      },
      {
        "text": "アノマリー",
        "furigana": "あのまりー"
      },
      {
        "text": "を",
        "furigana": null
      }
    ],
    "translation": "甚至連這個神奇的異常"
  },
  {
    "startTime": 106.98,
    "words": [
      {
        "text": "解",
        "furigana": "と"
      },
      {
        "text": "き",
        "furigana": null
      },
      {
        "text": "明",
        "furigana": "あ"
      },
      {
        "text": "かす",
        "furigana": null
      },
      {
        "text": "過程",
        "furigana": "かてい"
      },
      {
        "text": "さえ ",
        "furigana": null
      },
      {
        "text": "必要条件",
        "furigana": "ひつようじょうけん"
      },
      {
        "text": " です。",
        "furigana": null
      }
    ],
    "translation": "也是求解過程的必要條件"
  },
  {
    "startTime": 109.64,
    "words": [
      {
        "text": "「",
        "furigana": null
      },
      {
        "text": "三次元",
        "furigana": "さんじげん"
      },
      {
        "text": "((かっこ) ",
        "furigana": null
      },
      {
        "text": "立体",
        "furigana": "りったい"
      },
      {
        "text": ")における ",
        "furigana": null
      },
      {
        "text": "二点",
        "furigana": "にてん"
      },
      {
        "text": " AB ",
        "furigana": null
      },
      {
        "text": "間",
        "furigana": "かん"
      },
      {
        "text": "の",
        "furigana": null
      },
      {
        "text": "距離",
        "furigana": "きょり"
      },
      {
        "text": "を",
        "furigana": null
      },
      {
        "text": "求",
        "furigana": "もと"
      },
      {
        "text": "めよ。」",
        "furigana": null
      }
    ],
    "translation": "「在三維度(立體)中找到兩個點AB之間的距離。」"
  },
  {
    "startTime": 112.76,
    "words": [
      {
        "text": "的",
        "furigana": "てき"
      },
      {
        "text": "な",
        "furigana": null
      },
      {
        "text": "感",
        "furigana": "かん"
      },
      {
        "text": "じだと",
        "furigana": null
      },
      {
        "text": "思",
        "furigana": "おも"
      },
      {
        "text": "ってたのに ",
        "furigana": null
      },
      {
        "text": "座標",
        "furigana": "ざひょう"
      },
      {
        "text": "も",
        "furigana": null
      },
      {
        "text": "公式",
        "furigana": "こうしき"
      },
      {
        "text": "も",
        "furigana": null
      },
      {
        "text": "見当",
        "furigana": "みあ"
      },
      {
        "text": "たらないし",
        "furigana": null
      }
    ],
    "translation": "我還以為問題是⻑這個樣子 坐標或公式都證不出來"
  },
  {
    "startTime": 115.9,
    "words": [
      {
        "text": "参考",
        "furigana": "さんこう"
      },
      {
        "text": " ",
        "furigana": null
      },
      {
        "text": "資料",
        "furigana": "しりょう"
      },
      {
        "text": "にも",
        "furigana": null
      },
      {
        "text": "載",
        "furigana": "の"
      },
      {
        "text": "っ",
        "furigana": null
      },
      {
        "text": "ていないから",
        "furigana": null
      },
      {
        "text": " ",
        "furigana": null
      },
      {
        "text": "君",
        "furigana": "くん"
      },
      {
        "text": "と",
        "furigana": null
      },
      {
        "text": "生み出",
        "furigana": "うみだ"
      },
      {
        "text": "し",
        "furigana": null
      },
      {
        "text": "てみせたいじゃん",
        "furigana": null
      }
    ],
    "translation": "連參考資料上都沒有記錄 才會更想與你一同找出來呢"
  },
  {
    "startTime": 119.22,
    "words": [
      {
        "text": "三次元",
        "furigana": "さんじげん"
      },
      {
        "text": "((かっこ)",
        "furigana": null
      },
      {
        "text": "世界",
        "furigana": "せかい"
      },
      {
        "text": ")におけるこの",
        "furigana": null
      },
      {
        "text": "気持",
        "furigana": "きも"
      },
      {
        "text": "ちの",
        "furigana": null
      },
      {
        "text": "求",
        "furigana": "もと"
      },
      {
        "text": "め",
        "furigana": null
      },
      {
        "text": "方",
        "furigana": "かた"
      }
    ],
    "translation": "如何在三維度(世界)中求得這種感情"
  },
  {
    "startTime": 122.06,
    "words": [
      {
        "text": "○(まる)だって×(ばつ)だって ",
        "furigana": null
      },
      {
        "text": "不安",
        "furigana": "ふあん"
      },
      {
        "text": "にとって",
        "furigana": null
      },
      {
        "text": "イコール",
        "furigana": "いこーる"
      },
      {
        "text": "で",
        "furigana": null
      }
    ],
    "translation": "就算答案是○,亦或是× 焦慮的心情往往是呈現恆等值的"
  },
  {
    "startTime": 126.04,
    "words": [
      {
        "text": "近",
        "furigana": "ちか"
      },
      {
        "text": "くなって",
        "furigana": null
      },
      {
        "text": "遠",
        "furigana": "とお"
      },
      {
        "text": "くなって ",
        "furigana": null
      },
      {
        "text": "揺",
        "furigana": "ゆ"
      },
      {
        "text": "れるこの",
        "furigana": null
      },
      {
        "text": "気持",
        "furigana": "きも"
      },
      {
        "text": "ちの",
        "furigana": null
      },
      {
        "text": "針",
        "furigana": "はり"
      },
      {
        "text": "も ( ",
        "furigana": null
      },
      {
        "text": "条件",
        "furigana": "じょうけん"
      },
      {
        "text": " is ",
        "furigana": null
      },
      {
        "text": "明瞭",
        "furigana": "めいりょう"
      },
      {
        "text": " )",
        "furigana": null
      }
    ],
    "translation": "距離忽遠忽近 搖曳不定的這種感覺 (條件 is 明確)"
  },
  {
    "startTime": 133.28,
    "words": [
      {
        "text": "Steppin'",
        "furigana": null
      },
      {
        "text": "!",
        "furigana": null
      },
      {
        "text": "!",
        "furigana": null
      },
      {
        "text": " ",
        "furigana": null
      },
      {
        "text": "エモーション",
        "furigana": "えもーしょん"
      },
      {
        "text": "は",
        "furigana": null
      },
      {
        "text": "相愛",
        "furigana": "そうあい"
      },
      {
        "text": " ",
        "furigana": null
      },
      {
        "text": "性",
        "furigana": "せい"
      },
      {
        "text": "ミステイク",
        "furigana": "みすていく"
      }
    ],
    "translation": "Steppin'!! 舉止保留相愛性"
  },
  {
    "startTime": 135.68,
    "words": [
      {
        "text": "チューリングラブ",
        "furigana": "ちゅーりんぐらぶ"
      },
      {
        "text": " ",
        "furigana": null
      },
      {
        "text": "騒",
        "furigana": "さわ"
      },
      {
        "text": "ぎ",
        "furigana": null
      },
      {
        "text": "出",
        "furigana": "だ"
      },
      {
        "text": "し",
        "furigana": null
      },
      {
        "text": "た",
        "furigana": null
      },
      {
        "text": "胸",
        "furigana": "むね"
      },
      {
        "text": "の",
        "furigana": null
      },
      {
        "text": "痛",
        "furigana": "いた"
      },
      {
        "text": "く",
        "furigana": null
      },
      {
        "text": "なるほど",
        "furigana": null
      }
    ],
    "translation": "Turing Love 躁動的胸口越發疼痛的話"
  },
  {
    "startTime": 139.54,
    "words": [
      {
        "text": "証明",
        "furigana": "しょうめい"
      },
      {
        "text": " はいまも ",
        "furigana": null
      },
      {
        "text": "確度",
        "furigana": "かくど"
      },
      {
        "text": "を",
        "furigana": null
      },
      {
        "text": "増",
        "furigana": "ま"
      },
      {
        "text": "しているようだ",
        "furigana": null
      }
    ],
    "translation": "越能夠代表這份證明的準確性"
  },
  {
    "startTime": 143.04,
    "words": [
      {
        "text": "曖昧",
        "furigana": "あいまい"
      },
      {
        "text": "も",
        "furigana": null
      },
      {
        "text": "除外",
        "furigana": "じょがい"
      },
      {
        "text": "して ",
        "furigana": null
      },
      {
        "text": "最大",
        "furigana": "さいだい"
      },
      {
        "text": "の",
        "furigana": null
      },
      {
        "text": "仮説",
        "furigana": "かせつ"
      },
      {
        "text": "を",
        "furigana": null
      }
    ],
    "translation": "將曖昧的因素剔除 用最大限度的假設"
  },
  {
    "startTime": 146.62,
    "words": [
      {
        "text": "いま、ふたりなら ",
        "furigana": null
      },
      {
        "text": "実証",
        "furigana": "じっしょう"
      },
      {
        "text": " できそう",
        "furigana": null
      }
    ],
    "translation": "如果是現在的我們一定解得出來的"
  },
  {
    "startTime": 149.4,
    "words": [
      {
        "text": "チューリングラブ",
        "furigana": "ちゅーりんぐらぶ"
      },
      {
        "text": " ",
        "furigana": null
      },
      {
        "text": "見",
        "furigana": "み"
      },
      {
        "text": "つ",
        "furigana": null
      },
      {
        "text": "めあったったって",
        "furigana": null
      },
      {
        "text": "キリ",
        "furigana": "きり"
      },
      {
        "text": "ない",
        "furigana": null
      },
      {
        "text": "メロウ",
        "furigana": "めろう"
      }
    ],
    "translation": "Turing Love 互相凝視也不會結束的甜愛滋味"
  },
  {
    "startTime": 153.26,
    "words": [
      {
        "text": "ワットイズラブ",
        "furigana": "わっといずらぶ"
      },
      {
        "text": " ",
        "furigana": null
      },
      {
        "text": "いま",
        "furigana": null
      },
      {
        "text": " 123 ",
        "furigana": null
      },
      {
        "text": "で",
        "furigana": null
      },
      {
        "text": "証",
        "furigana": "しょう"
      },
      {
        "text": "そ",
        "furigana": null
      },
      {
        "text": "うか",
        "furigana": null
      }
    ],
    "translation": "What is Love 現在用123來證明吧"
  },
  {
    "startTime": 156.5,
    "words": [
      {
        "text": "言葉",
        "furigana": "ことば"
      },
      {
        "text": "で",
        "furigana": null
      },
      {
        "text": "生",
        "furigana": "う"
      },
      {
        "text": "み",
        "furigana": null
      },
      {
        "text": "出",
        "furigana": "だ"
      },
      {
        "text": "す",
        "furigana": null
      },
      {
        "text": "クエスチョン",
        "furigana": "くえすちょん"
      },
      {
        "text": " (",
        "furigana": null
      },
      {
        "text": "クエスチョン",
        "furigana": "くえすちょん"
      },
      {
        "text": "!)",
        "furigana": null
      }
    ],
    "translation": "言語之中所產生的問題 (Question!)"
  },
  {
    "startTime": 158.2,
    "words": [
      {
        "text": "ハート",
        "furigana": "はーと"
      },
      {
        "text": "で",
        "furigana": null
      },
      {
        "text": "高鳴",
        "furigana": "たかな"
      },
      {
        "text": "る",
        "furigana": null
      },
      {
        "text": "アンサー",
        "furigana": "あんさー"
      },
      {
        "text": " (",
        "furigana": null
      },
      {
        "text": "アンサー",
        "furigana": "あんさー"
      },
      {
        "text": "!)",
        "furigana": null
      }
    ],
    "translation": "心情激動所提出的解答 (Answer!)"
  },
  {
    "startTime": 159.86,
    "words": [
      {
        "text": "測",
        "furigana": "はか"
      },
      {
        "text": "ったって",
        "furigana": null
      },
      {
        "text": "不確定性",
        "furigana": "ふかくていせい"
      },
      {
        "text": " ぼくらの BPM",
        "furigana": null
      }
    ],
    "translation": "即使經由測量也不確定的 我們的 BPM"
  },
  {
    "startTime": 163.2,
    "words": [
      {
        "text": "チューリングラブ",
        "furigana": "ちゅーりんぐらぶ"
      },
      {
        "text": " ",
        "furigana": null
      },
      {
        "text": "宙",
        "furigana": "ちゅう"
      },
      {
        "text": " ",
        "furigana": null
      },
      {
        "text": "に",
        "furigana": null
      },
      {
        "text": "舞",
        "furigana": "ま"
      },
      {
        "text": "っ",
        "furigana": null
      },
      {
        "text": "たったってその",
        "furigana": null
      },
      {
        "text": "因果",
        "furigana": "いんが"
      },
      {
        "text": "も",
        "furigana": null
      }
    ],
    "translation": "Turing Love 即使是在空中漂浮的因果關係"
  },
  {
    "startTime": 166.64,
    "words": [
      {
        "text": "フォーリンラブ",
        "furigana": "ふぉーりんらぶ"
      },
      {
        "text": " いまは XYZ まで",
        "furigana": null
      },
      {
        "text": "解",
        "furigana": "わか"
      },
      {
        "text": "りそうだ",
        "furigana": null
      }
    ],
    "translation": "Fall in Love 現在我也能用XYZ解開了"
  },
  {
    "startTime": 170.02,
    "words": [
      {
        "text": "確",
        "furigana": "たし"
      },
      {
        "text": "かめさせて",
        "furigana": null
      },
      {
        "text": "ピタゴラス",
        "furigana": "ぴたごらす"
      },
      {
        "text": " (",
        "furigana": null
      },
      {
        "text": "ピタゴラス",
        "furigana": "ぴたごらす"
      },
      {
        "text": "!)",
        "furigana": null
      }
    ],
    "translation": "讓我們確定真理吧 畢達哥拉斯 (Pythagoras)!"
  },
  {
    "startTime": 171.66,
    "words": [
      {
        "text": "確",
        "furigana": "たし"
      },
      {
        "text": "かにさせて",
        "furigana": null
      },
      {
        "text": "リーマン",
        "furigana": "りーまん"
      },
      {
        "text": " (",
        "furigana": null
      },
      {
        "text": "リーマン",
        "furigana": "りーまん"
      },
      {
        "text": "!)",
        "furigana": null
      }
    ],
    "translation": "讓我們知道真相吧 黎曼 (Riemann)!"
  },
  {
    "startTime": 173.38,
    "words": [
      {
        "text": "予測",
        "furigana": "よそく"
      },
      {
        "text": "済",
        "furigana": "す"
      },
      {
        "text": "み",
        "furigana": null
      },
      {
        "text": "可変",
        "furigana": "かへん"
      },
      {
        "text": "性",
        "furigana": "せい"
      },
      {
        "text": " ",
        "furigana": null
      },
      {
        "text": "いま",
        "furigana": null
      },
      {
        "text": "触",
        "furigana": "ふ"
      },
      {
        "text": "れて",
        "furigana": null
      },
      {
        "text": "みる",
        "furigana": null
      }
    ],
    "translation": "嘗試預測這可變性 現在去試試看吧"
  },
  {
    "startTime": 176.28,
    "words": [
      {
        "text": "さあ ",
        "furigana": null
      },
      {
        "text": "証明",
        "furigana": "しょうめい"
      },
      {
        "text": " しよう ( ",
        "furigana": null
      },
      {
        "text": "証明",
        "furigana": "しょうめい"
      },
      {
        "text": " しよう) ",
        "furigana": null
      },
      {
        "text": "間違",
        "furigana": "まちが"
      },
      {
        "text": "いのないように",
        "furigana": null
      }
    ],
    "translation": "來證明吧 (證明吧) 為了不要弄錯"
  },
  {
    "startTime": 180.12,
    "words": [
      {
        "text": "証明",
        "furigana": "しょうめい"
      },
      {
        "text": " しよう ( ",
        "furigana": null
      },
      {
        "text": "証明",
        "furigana": "しょうめい"
      },
      {
        "text": " しよう) この ",
        "furigana": null
      },
      {
        "text": "感情",
        "furigana": "かんじょうぜんぶ"
      },
      {
        "text": " ",
        "furigana": null
      },
      {
        "text": "全部全部",
        "furigana": "ぜんぶ"
      }
    ],
    "translation": "證明吧 (證明吧) 將這份感情的全部全部"
  },
  {
    "startTime": 183.44,
    "words": [
      {
        "text": "証明",
        "furigana": "しょうめい"
      },
      {
        "text": " しよう ( ",
        "furigana": null
      },
      {
        "text": "証明",
        "furigana": "しょうめい"
      },
      {
        "text": " しよう) ",
        "furigana": null
      },
      {
        "text": "正解",
        "furigana": "せいかい"
      },
      {
        "text": "があるなら",
        "furigana": null
      }
    ],
    "translation": "證明吧 (證明吧) 如果答案是正確的話"
  },
  {
    "startTime": 186.9,
    "words": [
      {
        "text": "証明",
        "furigana": "しょうめい"
      },
      {
        "text": " しよう ( ",
        "furigana": null
      },
      {
        "text": "証明",
        "furigana": "しょうめい"
      },
      {
        "text": " しよう) ",
        "furigana": null
      },
      {
        "text": "推測",
        "furigana": "すいそく"
      },
      {
        "text": "を",
        "furigana": null
      },
      {
        "text": "超",
        "furigana": "こ"
      },
      {
        "text": "えて!",
        "furigana": null
      }
    ],
    "translation": "證明吧 (證明吧) 超出推測範圍!"
  },
  {
    "startTime": 190.68,
    "words": [
      {
        "text": "証明",
        "furigana": "しょうめい"
      },
      {
        "text": " しよう ( ",
        "furigana": null
      },
      {
        "text": "証明",
        "furigana": "しょうめい"
      },
      {
        "text": " しよう) ",
        "furigana": null
      },
      {
        "text": "間違",
        "furigana": "まちが"
      },
      {
        "text": "いのないように",
        "furigana": null
      }
    ],
    "translation": "證明吧 (證明吧) 為了不會搞錯"
  },
  {
    "startTime": 193.62,
    "words": [
      {
        "text": "証明",
        "furigana": "しょうめい"
      },
      {
        "text": " しよう ( ",
        "furigana": null
      },
      {
        "text": "証明",
        "furigana": "しょうめい"
      },
      {
        "text": " しよう) この ",
        "furigana": null
      },
      {
        "text": "感情",
        "furigana": "かんじょうぜんぶ"
      },
      {
        "text": " ",
        "furigana": null
      },
      {
        "text": "全部全部",
        "furigana": "ぜんぶ"
      }
    ],
    "translation": "證明吧 (證明吧) 將這份感情的全部全部"
  },
  {
    "startTime": 197.06,
    "words": [
      {
        "text": "証明",
        "furigana": "しょうめい"
      },
      {
        "text": " しよう ( ",
        "furigana": null
      },
      {
        "text": "証明",
        "furigana": "しょうめい"
      },
      {
        "text": " しよう) ",
        "furigana": null
      },
      {
        "text": "正解",
        "furigana": "せいかい"
      },
      {
        "text": "があるなら",
        "furigana": null
      }
    ],
    "translation": "證明吧 (證明吧) 如果有正確解答"
  },
  {
    "startTime": 200.42,
    "words": [
      {
        "text": "証明",
        "furigana": "しょうめい"
      },
      {
        "text": " しよう ( ",
        "furigana": null
      },
      {
        "text": "証明",
        "furigana": "しょうめい"
      },
      {
        "text": " しよう) ",
        "furigana": null
      },
      {
        "text": "シンプル",
        "furigana": "しんぷる"
      },
      {
        "text": "な Q.E.D.",
        "furigana": null
      }
    ],
    "translation": "證明吧 (證明吧) 簡單的 Q.E.D."
  }
]